sshepherd/__init__.py
sshepherd/errors.py
sshepherd/ssh.py
sshepherd-0.2.data/scripts/sshepherd
sshepherd-0.2.dist-info/LICENSE.md
sshepherd-0.2.dist-info/METADATA
sshepherd-0.2.dist-info/WHEEL
sshepherd-0.2.dist-info/top_level.txt
sshepherd-0.2.dist-info/RECORD
