Metadata-Version: 2.1
Name: sshepherd
Version: 0.2
Summary: SSHepherd: Automated SSH User Management
Home-page: https://github.com/drpresq/sshepherd
Author: George
Author-email: drpresq@gmail.com
License: UNKNOWN
Platform: UNKNOWN
Classifier: Development Status :: 5 - Production/Stable
Classifier: Intended Audience :: Information Technology
Classifier: Intended Audience :: System Administrators
Classifier: License :: OSI Approved :: BSD License
Classifier: Operating System :: OS Independent
Classifier: Programming Language :: Python :: 3.6
Classifier: Programming Language :: Python :: 3.7
Classifier: Programming Language :: Python :: 3.8
Classifier: Programming Language :: Python :: 3.9
Classifier: Programming Language :: Python :: 3.10
Classifier: Topic :: Utilities
License-File: LICENSE.md
Requires-Dist: paramiko (>=2.7.2)
Requires-Dist: scp (==0.13.6)
Provides-Extra: dev
Requires-Dist: pytest (>=6.2.4) ; extra == 'dev'
